{
 "modo": "ao_vivo",
 "gerado_em": "2026-07-22T15:00:00",
 "hora_modelo": "2026-07-22T15:00:00",
 "hora_alvo": "2026-07-22T17:00:00",
 "consultado_em": "2026-07-22T20:02:53",
 "telemetria_ultima_em": "2026-07-22T19:45:00",
 "telemetria_ultima_nivel_cm": 1819,
 "idade_telemetria_min": 18,
 "status_dados": "telemetria recente",
 "estacao": "86510000",
 "local": "Muçum",
 "horizonte": "2h",
 "rotulo": "2h",
 "horizonte_h": 2,
 "tipo": "ALT",
 "modelo": "MUC_H2_ALT_STC002_R2M001",
 "combo": "MUC_H2_ALT_STC002",
 "bankfull_cm": 500,
 "nivel_modelo_cm": 1843,
 "nivel_rio_agora_cm": 1819,
 "nivel_rio_agora_em": "2026-07-22T19:45:00",
 "nivel_atual_cm": 1843,
 "nivel_previsto_cm": 2242,
 "inputs_total": 10,
 "inputs_faltantes_n": 0,
 "inputs_faltantes": [],
 "estacoes_status": [],
 "status": "ok",
 "aviso": "EXPERIMENTAL — não é alerta oficial. Camada espacial da previsão de RNA para Muçum.",
 "delta_previsto_cm": 423.4,
 "passos": [
  [
   "2026-07-22T15:00:00",
   1819,
   2242
  ]
 ],
 "horizontes": {
  "2h": {
   "modo": "ao_vivo",
   "gerado_em": "2026-07-22T15:00:00",
   "hora_modelo": "2026-07-22T15:00:00",
   "hora_alvo": "2026-07-22T17:00:00",
   "consultado_em": "2026-07-22T20:02:53",
   "telemetria_ultima_em": "2026-07-22T19:45:00",
   "telemetria_ultima_nivel_cm": 1819,
   "idade_telemetria_min": 18,
   "status_dados": "telemetria recente",
   "estacao": "86510000",
   "local": "Muçum",
   "horizonte": "2h",
   "rotulo": "2h",
   "horizonte_h": 2,
   "tipo": "ALT",
   "modelo": "MUC_H2_ALT_STC002_R2M001",
   "combo": "MUC_H2_ALT_STC002",
   "bankfull_cm": 500,
   "nivel_modelo_cm": 1843,
   "nivel_rio_agora_cm": 1819,
   "nivel_rio_agora_em": "2026-07-22T19:45:00",
   "nivel_atual_cm": 1843,
   "nivel_previsto_cm": 2242,
   "inputs_total": 10,
   "inputs_faltantes_n": 0,
   "inputs_faltantes": [],
   "estacoes_status": [],
   "status": "ok",
   "aviso": "EXPERIMENTAL — não é alerta oficial. Camada espacial da previsão de RNA para Muçum.",
   "delta_previsto_cm": 423.4,
   "passos": [
    [
     "2026-07-22T15:00:00",
     1819,
     2242
    ]
   ]
  },
  "4h": {
   "modo": "ao_vivo",
   "gerado_em": "2026-07-22T15:00:00",
   "hora_modelo": "2026-07-22T15:00:00",
   "hora_alvo": "2026-07-22T19:00:00",
   "consultado_em": "2026-07-22T20:02:53",
   "telemetria_ultima_em": "2026-07-22T19:45:00",
   "telemetria_ultima_nivel_cm": 1819,
   "idade_telemetria_min": 18,
   "status_dados": "telemetria recente",
   "estacao": "86510000",
   "local": "Muçum",
   "horizonte": "4h",
   "rotulo": "4h",
   "horizonte_h": 4,
   "tipo": "ALT",
   "modelo": "MUC_H4_ALT_STC009_R2M014",
   "combo": "MUC_H4_ALT_STC009",
   "bankfull_cm": 500,
   "nivel_modelo_cm": 1843,
   "nivel_rio_agora_cm": 1819,
   "nivel_rio_agora_em": "2026-07-22T19:45:00",
   "nivel_atual_cm": 1843,
   "nivel_previsto_cm": 1985,
   "inputs_total": 13,
   "inputs_faltantes_n": 0,
   "inputs_faltantes": [],
   "estacoes_status": [],
   "status": "ok",
   "aviso": "EXPERIMENTAL — não é alerta oficial. Camada espacial da previsão de RNA para Muçum.",
   "delta_previsto_cm": 165.7,
   "passos": [
    [
     "2026-07-22T15:00:00",
     1819,
     1985
    ]
   ]
  }
 }
}